ontoviz/__init__.py
ontoviz/_version.py
ontoviz/graph.py
ontoviz/graph_element.py
ontoviz/namespace.py
ontoviz/to_dot.py
ontoviz/utils.py
ontoviz-2022.1.3.dist-info/AUTHORS.md
ontoviz-2022.1.3.dist-info/LICENSE
ontoviz-2022.1.3.dist-info/METADATA
ontoviz-2022.1.3.dist-info/WHEEL
ontoviz-2022.1.3.dist-info/entry_points.txt
ontoviz-2022.1.3.dist-info/top_level.txt
ontoviz-2022.1.3.dist-info/RECORD
